plugger/__init__.py
plugger/core.py
plugger-0.4.1.dist-info/DESCRIPTION.rst
plugger-0.4.1.dist-info/METADATA
plugger-0.4.1.dist-info/RECORD
plugger-0.4.1.dist-info/WHEEL
plugger-0.4.1.dist-info/metadata.json
plugger-0.4.1.dist-info/top_level.txt
