Metadata-Version: 2.0
Name: plugger
Version: 0.4.1
Summary: Plugger:  A simple setuptools-entrypoints-based plugin manager.
Home-page: https://github.com/toejough/plugger
Author: toejough
Author-email: toejough@gmail.com
License: UNKNOWN
Keywords: setuptools entrypoint plugin
Platform: UNKNOWN
Classifier: Development Status :: 3 - Alpha
Classifier: Intended Audience :: Developers
Classifier: License :: OSI Approved :: Apache Software License
Classifier: Programming Language :: Python :: 3
Classifier: Programming Language :: Python :: 3.6
Provides-Extra: static-analysis
Requires-Dist: pylint; extra == 'static-analysis'
Requires-Dist: flake8; extra == 'static-analysis'
Requires-Dist: flake8-docstrings; extra == 'static-analysis'
Requires-Dist: pep8-naming; extra == 'static-analysis'
Requires-Dist: mccabe; extra == 'static-analysis'
Requires-Dist: flake8-import-order; extra == 'static-analysis'
Requires-Dist: flake8-bugbear; extra == 'static-analysis'
Requires-Dist: flake8-tidy-imports; extra == 'static-analysis'
Requires-Dist: flake8-quotes; extra == 'static-analysis'
Requires-Dist: flake8-commas; extra == 'static-analysis'
Requires-Dist: flake8-comprehensions; extra == 'static-analysis'
Requires-Dist: flake8-todo; extra == 'static-analysis'
Requires-Dist: flake8-debugger; extra == 'static-analysis'
Requires-Dist: flake8-blind-except; extra == 'static-analysis'
Requires-Dist: flake8-string-format; extra == 'static-analysis'
Requires-Dist: flake8-tuple; extra == 'static-analysis'
Requires-Dist: flake8-builtins; extra == 'static-analysis'
Requires-Dist: flake8-coding; extra == 'static-analysis'
Requires-Dist: flake8-deprecated; extra == 'static-analysis'
Requires-Dist: flake8-mutable; extra == 'static-analysis'
Requires-Dist: dodgy; extra == 'static-analysis'
Requires-Dist: vulture; extra == 'static-analysis'
Requires-Dist: mypy; extra == 'static-analysis'
Requires-Dist: pocketwalk; extra == 'static-analysis'
Provides-Extra: testing
Requires-Dist: dado; extra == 'testing'
Requires-Dist: pytest; extra == 'testing'
